MANIFEST.in
README.md
setup.cfg
setup.py
versioneer.py
pynmet/__init__.py
pynmet/_version.py
pynmet/calculations.py
pynmet/cli.py
pynmet/getdata.py
pynmet/inmet.py
pynmet/validation.py
pynmet.egg-info/PKG-INFO
pynmet.egg-info/SOURCES.txt
pynmet.egg-info/dependency_links.txt
pynmet.egg-info/entry_points.txt
pynmet.egg-info/not-zip-safe
pynmet.egg-info/requires.txt
pynmet.egg-info/top_level.txt
pynmet/data/estacoes.csv