Metadata-Version: 1.1
Name: pynmet
Version: 0.3.9
Summary: Python code to retrieve and plot inmet meteorological data
Home-page: https://gitlab.com/sehnem/pynmet/
Author: Josué M. Sehnem
Author-email: josue@sehnem.com
License: GPLv3
Download-URL: https://gitlab.com/sehnem/pynmet/-/archive/0.3.9/pynmet-0.3.9.tar.gz
Platform: UNKNOWN
Classifier: Development Status :: 2 - Pre-Alpha
Classifier: Operating System :: POSIX :: Linux
Classifier: License :: OSI Approved :: Python Software Foundation License
Classifier: License :: OSI Approved :: GNU General Public License (GPL)
Classifier: Intended Audience :: Developers
Classifier: Programming Language :: Python :: 3
Classifier: Topic :: Software Development
Classifier: Topic :: System :: Hardware
